Metadata-Version: 2.1
Name: cobraz-pulumi-gcp-scaffold
Version: 0.3.5
Summary: UNKNOWN
Home-page: UNKNOWN
License: UNKNOWN
Platform: UNKNOWN
